{
    "Dynamic Table": {
        "checkpoints": [
            {
                "steps": 499962,
                "file_path": "results/0.7.22-Colab02/Dynamic Table/Dynamic Table-499962.onnx",
                "reward": 0.5161826902634052,
                "creation_time": 1711362898.3499928,
                "auxillary_file_paths": [
                    "results/0.7.22-Colab02/Dynamic Table/Dynamic Table-499962.pt"
                ]
            },
            {
                "steps": 999938,
                "file_path": "results/0.7.22-Colab02/Dynamic Table/Dynamic Table-999938.onnx",
                "reward": 0.712738556876069,
                "creation_time": 1711367154.7976584,
                "auxillary_file_paths": [
                    "results/0.7.22-Colab02/Dynamic Table/Dynamic Table-999938.pt"
                ]
            },
            {
                "steps": 1499936,
                "file_path": "results/0.7.22-Colab02/Dynamic Table/Dynamic Table-1499936.onnx",
                "reward": 0.5932671442153115,
                "creation_time": 1711371317.394382,
                "auxillary_file_paths": [
                    "results/0.7.22-Colab02/Dynamic Table/Dynamic Table-1499936.pt"
                ]
            },
            {
                "steps": 1999960,
                "file_path": "results/0.7.22-Colab02/Dynamic Table/Dynamic Table-1999960.onnx",
                "reward": 0.7043283851299849,
                "creation_time": 1711375435.804036,
                "auxillary_file_paths": [
                    "results/0.7.22-Colab02/Dynamic Table/Dynamic Table-1999960.pt"
                ]
            },
            {
                "steps": 2126046,
                "file_path": "results/0.7.22-Colab02/Dynamic Table/Dynamic Table-2126046.onnx",
                "reward": 0.8302106780310472,
                "creation_time": 1711376460.3124523,
                "auxillary_file_paths": [
                    "results/0.7.22-Colab02/Dynamic Table/Dynamic Table-2126046.pt"
                ]
            }
        ],
        "final_checkpoint": {
            "steps": 2126046,
            "file_path": "results/0.7.22-Colab02/Dynamic Table.onnx",
            "reward": 0.8302106780310472,
            "creation_time": 1711376460.3124523,
            "auxillary_file_paths": [
                "results/0.7.22-Colab02/Dynamic Table/Dynamic Table-2126046.pt"
            ]
        }
    },
    "metadata": {
        "stats_format_version": "0.3.0",
        "mlagents_version": "1.0.0",
        "torch_version": "2.2.1+cu121"
    }
}